tevatron/__init__.py
tevatron/arguments.py
tevatron/data.py
tevatron/loss.py
tevatron/modeling.py
tevatron/trainer.py
tevatron/datasets/__init__.py
tevatron/datasets/dataset.py
tevatron/datasets/preprocessor.py
tevatron/driver/__init__.py
tevatron/driver/encode.py
tevatron/driver/jax_encode.py
tevatron/driver/jax_train.py
tevatron/driver/train.py
tevatron/faiss_retriever/__init__.py
tevatron/faiss_retriever/__main__.py
tevatron/faiss_retriever/reducer.py
tevatron/faiss_retriever/retriever.py
tevatron/preprocessor/__init__.py
tevatron/preprocessor/preprocessor_tsv.py
tevatron/tevax/__init__.py
tevatron/tevax/loss.py
tevatron/tevax/training.py
tevatron/utils/__init__.py
tevatron/utils/convert_from_dpr.py
tevatron/utils/format/__init__.py
tevatron/utils/format/convert_result_to_trec.py
tevatron-0.1.0.dist-info/LICENSE
tevatron-0.1.0.dist-info/METADATA
tevatron-0.1.0.dist-info/WHEEL
tevatron-0.1.0.dist-info/top_level.txt
tevatron-0.1.0.dist-info/RECORD
