Metadata-Version: 2.1
Name: tevatron
Version: 0.1.0
Summary: Tevatron: A toolkit for learning and running deep dense retrieval models.
Home-page: https://github.com/texttron/tevatron
Author: Luyu Gao
Author-email: luyug@cs.cmu.edu
License: Apache 2.0
Platform: UNKNOWN
Requires-Python: >=3.7
License-File: LICENSE
Requires-Dist: transformers (>=4.10.0)
Requires-Dist: datasets (>=1.1.3)
